redix_client/__init__.py
redix_client/client.py
redix_client/enums.py
redix_client/exceptions.py
redix_client/models.py
redix_client/redix_api.py
redix_client-2.1.1.dist-info/METADATA
redix_client-2.1.1.dist-info/WHEEL
redix_client-2.1.1.dist-info/top_level.txt
redix_client-2.1.1.dist-info/RECORD
