Metadata-Version: 2.4
Name: redix-client
Version: 2.1.1
Summary: Python client for Redix Universal Healthcare Conversion API
Author-email: "Redix International, Inc." <sales@redix.com>
License: MIT
Project-URL: Homepage, https://demo.redix.com
Classifier: License :: OSI Approved :: MIT License
Classifier: Operating System :: OS Independent
Classifier: Programming Language :: Python :: 3
Requires-Python: >=3.7
Requires-Dist: httpx<1.0,>=0.23.0
Requires-Dist: pydantic<2.0,>=1.9.0
